itertoools/__init__.py
itertoools-0.1.0.dist-info/licenses/LICENSE
itertoools-0.1.0.dist-info/METADATA
itertoools-0.1.0.dist-info/WHEEL
itertoools-0.1.0.dist-info/top_level.txt
itertoools-0.1.0.dist-info/RECORD
