Metadata-Version: 2.4
Name: itertoools
Version: 0.1.0
Summary: Набор функций для решения задач по теории вероятностей
Home-page: https://github.com/nikakimvv/exam_teorver
Author: HIOL
Author-email: HIOL <hiol.dev@gmail.com>
Maintainer-email: HIOL <hiol.dev@gmail.com>
License: MIT
Project-URL: Homepage, https://github.com/nikakimvv/exam_teorver
Project-URL: Documentation, https://github.com/nikakimvv/exam_teorver
Project-URL: Repository, https://github.com/nikakimvv/exam_teorver.git
Project-URL: Bug Tracker, https://github.com/nikakimvv/exam_teorver/issues
Keywords: probability,statistics,mathematics,monte-carlo
Classifier: Development Status :: 3 - Alpha
Classifier: Intended Audience :: Education
Classifier: License :: OSI Approved :: MIT License
Classifier: Operating System :: OS Independent
Classifier: Programming Language :: Python :: 3
Classifier: Programming Language :: Python :: 3.8
Classifier: Programming Language :: Python :: 3.9
Classifier: Programming Language :: Python :: 3.10
Classifier: Programming Language :: Python :: 3.11
Classifier: Topic :: Scientific/Engineering :: Mathematics
Requires-Python: >=3.8
License-File: LICENSE
Requires-Dist: sympy
Requires-Dist: scipy
Requires-Dist: numpy
Dynamic: author
Dynamic: home-page
Dynamic: license-file
Dynamic: requires-python
